mongeasy/__init__.py
mongeasy/base_dict.py
mongeasy/connection.py
mongeasy/core.py
mongeasy/document.py
mongeasy/dynamics.py
mongeasy/exceptions.py
mongeasy/lazy_resultlist.py
mongeasy/resultlist.py
mongeasy/examples/__init__.py
mongeasy/extensions/__init__.py
mongeasy/plugins/__init__.py
mongeasy/plugins/plugin_manager.py
mongeasy/plugins/registry.py
mongeasy/utils/__init__.py
mongeasy/utils/utils.py
sample_plugins/__init__.py
sample_plugins/before_save_plugin.py
sample_plugins/connection_plugin.py
sample_plugins/delete_plugin.py
sample_plugins/init_plugin.py
sample_plugins/pydantic_validator.py
sample_plugins/query_plugin.py
sample_plugins/save_plugin.py
sample_plugins/validator_plugin.py
tests/__init__.py
tests/test_mongeasy.py
tests/test_plugins.py
mongeasy-0.2.4.dist-info/LICENSE
mongeasy-0.2.4.dist-info/METADATA
mongeasy-0.2.4.dist-info/WHEEL
mongeasy-0.2.4.dist-info/top_level.txt
mongeasy-0.2.4.dist-info/RECORD
