Metadata-Version: 2.1
Name: mongeasy
Version: 0.2.4
Summary: Easy to use wrapper around pymongo for easy access to MongoDB.
Home-page: https://github.com/artheadsweden/mongeasy
Author: Joakim Wassberg
Author-email: joakim.wassberg@arthead.se
License: MIT
Classifier: Development Status :: 4 - Beta
Classifier: Intended Audience :: Developers
Classifier: License :: OSI Approved :: MIT License
Classifier: Programming Language :: Python :: 3
Classifier: Programming Language :: Python :: 3.8
Classifier: Programming Language :: Python :: 3.9
Classifier: Programming Language :: Python :: 3.10
Classifier: Programming Language :: Python :: 3.11
Classifier: Topic :: Database
License-File: LICENSE
Requires-Dist: bleach (==6.0.0)
Requires-Dist: build (==0.10.0)
Requires-Dist: certifi (==2022.12.7)
Requires-Dist: charset-normalizer (==3.1.0)
Requires-Dist: click (==8.1.3)
Requires-Dist: colorama (==0.4.6)
Requires-Dist: dnspython (==2.3.0)
Requires-Dist: docutils (==0.19)
Requires-Dist: ghp-import (==2.1.0)
Requires-Dist: idna (==3.4)
Requires-Dist: import-string (==0.1.0)
Requires-Dist: importlib-metadata (==6.4.1)
Requires-Dist: iniconfig (==2.0.0)
Requires-Dist: jaraco.classes (==3.2.3)
Requires-Dist: keyring (==23.13.1)
Requires-Dist: Markdown (==3.3.7)
Requires-Dist: markdown-it-py (==2.2.0)
Requires-Dist: MarkupSafe (==2.1.3)
Requires-Dist: mdurl (==0.1.2)
Requires-Dist: mergedeep (==1.3.4)
Requires-Dist: mkdocs (==1.4.2)
Requires-Dist: more-itertools (==9.1.0)
Requires-Dist: packaging (==23.1)
Requires-Dist: pkginfo (==1.9.6)
Requires-Dist: pluggy (==1.2.0)
Requires-Dist: pydantic (==1.10.9)
Requires-Dist: Pygments (==2.15.0)
Requires-Dist: pymongo (==4.3.3)
Requires-Dist: pyparsing (==3.0.9)
Requires-Dist: pyproject-hooks (==1.0.0)
Requires-Dist: pytest (==7.3.1)
Requires-Dist: python-dateutil (==2.8.2)
Requires-Dist: pywin32-ctypes (==0.2.0)
Requires-Dist: PyYAML (==6.0)
Requires-Dist: pyyaml-env-tag (==0.1)
Requires-Dist: readme-renderer (==37.3)
Requires-Dist: requests (==2.28.2)
Requires-Dist: requests-toolbelt (==0.10.1)
Requires-Dist: rfc3986 (==2.0.0)
Requires-Dist: rich (==13.3.4)
Requires-Dist: six (==1.16.0)
Requires-Dist: twine (==4.0.2)
Requires-Dist: typing-extensions (==4.6.3)
Requires-Dist: urllib3 (==1.26.15)
Requires-Dist: watchdog (==3.0.0)
Requires-Dist: webencodings (==0.5.1)
Requires-Dist: zipp (==3.15.0)
